README.md
setup.py
devground/__init__.py
devground.egg-info/PKG-INFO
devground.egg-info/SOURCES.txt
devground.egg-info/dependency_links.txt
devground.egg-info/top_level.txt